readme_ation/__init__.py
readme_ation/__main__.py
readme_ation/generator.py
readme_ation/utils.py
readme_ation-0.1.18.dist-info/LICENSE.txt
readme_ation-0.1.18.dist-info/METADATA
readme_ation-0.1.18.dist-info/WHEEL
readme_ation-0.1.18.dist-info/top_level.txt
readme_ation-0.1.18.dist-info/RECORD
