Metadata-Version: 2.1
Name: readme-ation
Version: 0.1.18
Summary: A README.md generation tool
Home-page: https://github.com/chuckfinca/readme-ation
Author: Charles Feinn
Author-email: chuckfinca@gmail.com
Classifier: Programming Language :: Python :: 3
Classifier: License :: OSI Approved :: MIT License
Classifier: Operating System :: OS Independent
Requires-Python: >=3.8
License-File: LICENSE.txt
Requires-Dist: pkg-vers>=0.1.0
